agentleman/__init__.py
agentleman-0.1.0.dist-info/METADATA
agentleman-0.1.0.dist-info/WHEEL
agentleman-0.1.0.dist-info/RECORD
