Metadata-Version: 2.3
Name: agentleman
Version: 0.1.0
Summary: Python agent for coding and research
Author: Michał Murawski
Author-email: mmurawski777@gmail.com
Requires-Python: >=3.12
Classifier: Programming Language :: Python :: 3
Classifier: Programming Language :: Python :: 3.12
Classifier: Programming Language :: Python :: 3.13
